find_known_secrets/__init__.py
find_known_secrets/__main__.py
find_known_secrets/__version__.py
find_known_secrets/_secrets.py
find_known_secrets/main.py
find_known_secrets/searcher.py
find_known_secrets-1.3.0.dist-info/LICENSE
find_known_secrets-1.3.0.dist-info/METADATA
find_known_secrets-1.3.0.dist-info/WHEEL
find_known_secrets-1.3.0.dist-info/entry_points.txt
find_known_secrets-1.3.0.dist-info/RECORD
